matflow_defdap/__init__.py
matflow_defdap/_version.py
matflow_defdap/main.py
matflow_defdap/scripting.py
matflow_defdap/snippets/get_DIC_image.py
matflow_defdap/snippets/get_EBSD_image.py
matflow_defdap/snippets/link_EBSD_DIC_maps.py
matflow_defdap/snippets/load_DIC_map.py
matflow_defdap/snippets/load_EBSD_map.py
matflow_defdap-0.1.8.dist-info/LICENSE
matflow_defdap-0.1.8.dist-info/METADATA
matflow_defdap-0.1.8.dist-info/WHEEL
matflow_defdap-0.1.8.dist-info/entry_points.txt
matflow_defdap-0.1.8.dist-info/top_level.txt
matflow_defdap-0.1.8.dist-info/RECORD
